rtmdet/__init__.py
rtmdet/backbone.py
rtmdet/checkpoint_utils.py
rtmdet/constants.py
rtmdet/head.py
rtmdet/neck.py
rtmdet/rtmdet.py
rtmdet/typings.py
rtmdet/utils.py
rtmdet/config/__init__.py
rtmdet/config/rtmdet_config.py
rtmdet/config/defaults/rtmdet_large.yaml
rtmdet/config/defaults/rtmdet_medium.yaml
rtmdet/config/defaults/rtmdet_small.yaml
rtmdet/config/defaults/rtmdet_tiny.yaml
rtmdet/layers/__init__.py
rtmdet/layers/channel_attention.py
rtmdet/layers/conv_module.py
rtmdet/layers/csp_layer.py
rtmdet/layers/csp_next_block.py
rtmdet/layers/sppf.py
rtmdet-0.3.0.dist-info/licenses/LICENSE
rtmdet-0.3.0.dist-info/WHEEL
rtmdet-0.3.0.dist-info/METADATA
rtmdet-0.3.0.dist-info/RECORD
