Metadata-Version: 2.4
Name: rtmdet
Version: 0.3.0
Summary: RTMDet Pytorch Implementation
Author: Alessio Arcara
Requires-Python: >=3.10
License-Expression: MIT
License-File: LICENSE
Requires-Dist: numpy<2.0
Requires-Dist: pydantic>=2.11.9
Requires-Dist: pyyaml>=6.0.2
Requires-Dist: torch>=2.8.0
Requires-Dist: torchvision>=0.23.0
Project-URL: Homepage, https://github.com/alessioarcara/rtmdet_pytorch_implementation
Project-URL: Repository, https://github.com/alessioarcara/rtmdet_pytorch_implementation.git
